README.md
setup.py
ess_message_consumer/__init__.py
ess_message_consumer/application.py
ess_message_consumer/console_output.py
ess_message_consumer/consumer.py
ess_message_consumer/deserializer.py
ess_message_consumer/producer.py
ess_message_consumer/topic_watchdog.py
ess_message_consumer/utils.py
ess_message_consumer.egg-info/PKG-INFO
ess_message_consumer.egg-info/SOURCES.txt
ess_message_consumer.egg-info/dependency_links.txt
ess_message_consumer.egg-info/entry_points.txt
ess_message_consumer.egg-info/requires.txt
ess_message_consumer.egg-info/top_level.txt