Metadata-Version: 2.1
Name: ess-message-consumer
Version: 0.1.3
Summary: Kafka consumer to handle ESS flatbuffer messages and provide a rich display on console.
Home-page: UNKNOWN
Author: Ebad Kamil
Author-email: ebad.kamil@ess.eu
Maintainer: Ebad Kamil
License: UNKNOWN
Platform: UNKNOWN
Requires-Python: >=3.6
Provides-Extra: test
